{
  "clientes": [
    {
      "nome": "Jakson Laquini",
      "cpf": "14177788866",
      "dataNascimento": "1993-03-05T03:00:00.000Z",
      "rendaMensal": 4000,
      "email": "jakson@gmail.com",
      "dataCadastro": "2023-04-27T22:04:00.288Z",
      "id": "KDf2Pfm"
    },
    {
      "nome": "Ana Maria Silva",
      "cpf": "36552555545",
      "dataNascimento": "1992-03-05T03:00:00.000Z",
      "rendaMensal": 22325,
      "email": "j@n",
      "dataCadastro": "2023-04-27T21:59:47.666Z",
      "id": "kZYwuqz"
    }
  ]
}